{
  "$ref": "#/definitions/CreateEventRequest",
  "definitions": {
    "CreateEventRequest": {
      "type": "object",
      "properties": {
        "event_type": {
          "type": "string",
          "minLength": 1
        },
        "source_system": {
          "type": "string",
          "minLength": 1
        },
        "payload": {
          "type": "object",
          "additionalProperties": {}
        }
      },
      "required": [
        "event_type",
        "source_system",
        "payload"
      ],
      "additionalProperties": false
    }
  },
  "$schema": "http://json-schema.org/draft-07/schema#"
}